{
    "interactionModel": {
        "languageModel": {
            "invocationName": "side cook",
            "intents": [
                {
                    "name": "AMAZON.CancelIntent",
                    "samples": []
                },
                {
                    "name": "AMAZON.HelpIntent",
                    "samples": []
                },
                {
                    "name": "AMAZON.StopIntent",
                    "samples": []
                },
                {
                    "name": "SearchIntent",
                    "slots": [
                        {
                            "name": "Food",
                            "type": "AMAZON.Food"
                        }
                    ],
                    "samples": [
                        "recipe of {Food}",
                        "search for {Food}",
                        "search"
                    ]
                },
                {
                    "name": "SelectRecipeIntent",
                    "slots": [
                        {
                            "name": "Recipe",
                            "type": "AMAZON.Food"
                        }
                    ],
                    "samples": [
                        "{Recipe}"
                    ]
                },
                {
                    "name": "SelectStepNumberIntent",
                    "slots": [
                        {
                            "name": "StepNumber",
                            "type": "AMAZON.NUMBER"
                        }
                    ],
                    "samples": [
                        "Step {StepNumber}",
                        "Go to step {StepNumber}"
                    ]
                },
                {
                    "name": "AMAZON.MoreIntent",
                    "samples": []
                },
                {
                    "name": "AMAZON.NavigateHomeIntent",
                    "samples": []
                },
                {
                    "name": "AMAZON.NavigateSettingsIntent",
                    "samples": []
                },
                {
                    "name": "AMAZON.NextIntent",
                    "samples": []
                },
                {
                    "name": "AMAZON.PageUpIntent",
                    "samples": []
                },
                {
                    "name": "AMAZON.PageDownIntent",
                    "samples": []
                },
                {
                    "name": "AMAZON.PreviousIntent",
                    "samples": []
                },
                {
                    "name": "AMAZON.ScrollRightIntent",
                    "samples": []
                },
                {
                    "name": "AMAZON.ScrollDownIntent",
                    "samples": []
                },
                {
                    "name": "AMAZON.ScrollLeftIntent",
                    "samples": []
                },
                {
                    "name": "AMAZON.ScrollUpIntent",
                    "samples": []
                },
                {
                    "name": "IngredientIntent",
                    "slots": [],
                    "samples": [
                        "list the ingredients",
                        "what are the ingredients",
                        "how many ingredients",
                        "ingredient",
                        "ingredients",
                        "show me the ingredients"
                    ]
                }
            ],
            "types": []
        }
    }
}